shell_shockers_utils/__init__.py
shell_shockers_utils/main.py
shell_shockers_utils-0.0.1.dist-info/METADATA
shell_shockers_utils-0.0.1.dist-info/WHEEL
shell_shockers_utils-0.0.1.dist-info/RECORD
